{
    "key": "group_67befebe5a425",
    "title": "Configuración tema",
    "fields": [
        {
            "key": "field_67beffb4fe1a4",
            "label": "Fonts",
            "name": "",
            "aria-label": "",
            "type": "tab",
            "instructions": "",
            "required": 0,
            "conditional_logic": 0,
            "wrapper": {
                "width": "",
                "class": "",
                "id": ""
            },
            "placement": "top",
            "endpoint": 1,
            "selected": 0
        },
        {
            "key": "field_67bf026f5dd71",
            "label": "Font Headers",
            "name": "fuente_titulares_regular",
            "aria-label": "",
            "type": "group",
            "instructions": "",
            "required": 0,
            "conditional_logic": 0,
            "wrapper": {
                "width": "33.33",
                "class": "",
                "id": ""
            },
            "layout": "block",
            "sub_fields": [
                {
                    "key": "field_67bf02925dd72",
                    "label": "WOFF2",
                    "name": "woff2",
                    "aria-label": "",
                    "type": "file",
                    "instructions": "",
                    "required": 0,
                    "conditional_logic": 0,
                    "wrapper": {
                        "width": "",
                        "class": "",
                        "id": ""
                    },
                    "return_format": "",
                    "library": "",
                    "min_size": "",
                    "max_size": "",
                    "mime_types": "",
                    "allow_in_bindings": 0
                },
                {
                    "key": "field_67bf02c35dd73",
                    "label": "WOFF",
                    "name": "woff",
                    "aria-label": "",
                    "type": "file",
                    "instructions": "",
                    "required": 0,
                    "conditional_logic": 0,
                    "wrapper": {
                        "width": "",
                        "class": "",
                        "id": ""
                    },
                    "return_format": "",
                    "library": "",
                    "min_size": "",
                    "max_size": "",
                    "mime_types": "",
                    "allow_in_bindings": 0
                },
                {
                    "key": "field_67bf02cb5dd74",
                    "label": "TTF",
                    "name": "ttf",
                    "aria-label": "",
                    "type": "file",
                    "instructions": "",
                    "required": 0,
                    "conditional_logic": 0,
                    "wrapper": {
                        "width": "",
                        "class": "",
                        "id": ""
                    },
                    "return_format": "",
                    "library": "",
                    "min_size": "",
                    "max_size": "",
                    "mime_types": "",
                    "allow_in_bindings": 0
                }
            ]
        },
        {
            "key": "field_67bf02f25dd79",
            "label": "Font Headers Bold",
            "name": "fuente_titulares_bold",
            "aria-label": "",
            "type": "group",
            "instructions": "",
            "required": 0,
            "conditional_logic": 0,
            "wrapper": {
                "width": "33.33",
                "class": "",
                "id": ""
            },
            "layout": "block",
            "sub_fields": [
                {
                    "key": "field_67bf02f25dd7a",
                    "label": "WOFF2",
                    "name": "woff2",
                    "aria-label": "",
                    "type": "file",
                    "instructions": "",
                    "required": 0,
                    "conditional_logic": 0,
                    "wrapper": {
                        "width": "",
                        "class": "",
                        "id": ""
                    },
                    "return_format": "array",
                    "library": "all",
                    "min_size": "",
                    "max_size": "",
                    "mime_types": "",
                    "allow_in_bindings": 0
                },
                {
                    "key": "field_67bf02f25dd7b",
                    "label": "WOFF",
                    "name": "woff",
                    "aria-label": "",
                    "type": "file",
                    "instructions": "",
                    "required": 0,
                    "conditional_logic": 0,
                    "wrapper": {
                        "width": "",
                        "class": "",
                        "id": ""
                    },
                    "return_format": "array",
                    "library": "all",
                    "min_size": "",
                    "max_size": "",
                    "mime_types": "",
                    "allow_in_bindings": 0
                },
                {
                    "key": "field_67bf02f25dd7c",
                    "label": "TTF",
                    "name": "ttf",
                    "aria-label": "",
                    "type": "file",
                    "instructions": "",
                    "required": 0,
                    "conditional_logic": 0,
                    "wrapper": {
                        "width": "",
                        "class": "",
                        "id": ""
                    },
                    "return_format": "array",
                    "library": "all",
                    "min_size": "",
                    "max_size": "",
                    "mime_types": "",
                    "allow_in_bindings": 0
                }
            ]
        },
        {
            "key": "field_67bf02e15dd75",
            "label": "Font Headers Italic",
            "name": "fuente_titulares_italic",
            "aria-label": "",
            "type": "group",
            "instructions": "",
            "required": 0,
            "conditional_logic": 0,
            "wrapper": {
                "width": "33.33",
                "class": "",
                "id": ""
            },
            "layout": "block",
            "sub_fields": [
                {
                    "key": "field_67bf02e15dd76",
                    "label": "WOFF2",
                    "name": "woff2",
                    "aria-label": "",
                    "type": "file",
                    "instructions": "",
                    "required": 0,
                    "conditional_logic": 0,
                    "wrapper": {
                        "width": "",
                        "class": "",
                        "id": ""
                    },
                    "return_format": "",
                    "library": "",
                    "min_size": "",
                    "max_size": "",
                    "mime_types": "",
                    "allow_in_bindings": 0
                },
                {
                    "key": "field_67bf02e15dd77",
                    "label": "WOFF",
                    "name": "woff",
                    "aria-label": "",
                    "type": "file",
                    "instructions": "",
                    "required": 0,
                    "conditional_logic": 0,
                    "wrapper": {
                        "width": "",
                        "class": "",
                        "id": ""
                    },
                    "return_format": "",
                    "library": "",
                    "min_size": "",
                    "max_size": "",
                    "mime_types": "",
                    "allow_in_bindings": 0
                },
                {
                    "key": "field_67bf02e15dd78",
                    "label": "TTF",
                    "name": "ttf",
                    "aria-label": "",
                    "type": "file",
                    "instructions": "",
                    "required": 0,
                    "conditional_logic": 0,
                    "wrapper": {
                        "width": "",
                        "class": "",
                        "id": ""
                    },
                    "return_format": "",
                    "library": "",
                    "min_size": "",
                    "max_size": "",
                    "mime_types": "",
                    "allow_in_bindings": 0
                }
            ]
        },
        {
            "key": "field_67ed05dcf39e1",
            "label": "Font Text",
            "name": "fuente_texto_regular",
            "aria-label": "",
            "type": "group",
            "instructions": "",
            "required": 0,
            "conditional_logic": 0,
            "wrapper": {
                "width": "33.33",
                "class": "",
                "id": ""
            },
            "layout": "block",
            "sub_fields": [
                {
                    "key": "field_67ed05dcf39e2",
                    "label": "WOFF2",
                    "name": "woff2",
                    "aria-label": "",
                    "type": "file",
                    "instructions": "",
                    "required": 0,
                    "conditional_logic": 0,
                    "wrapper": {
                        "width": "",
                        "class": "",
                        "id": ""
                    },
                    "return_format": "array",
                    "library": "all",
                    "min_size": "",
                    "max_size": "",
                    "mime_types": "",
                    "allow_in_bindings": 0
                },
                {
                    "key": "field_67ed05dcf39e3",
                    "label": "WOFF",
                    "name": "woff",
                    "aria-label": "",
                    "type": "file",
                    "instructions": "",
                    "required": 0,
                    "conditional_logic": 0,
                    "wrapper": {
                        "width": "",
                        "class": "",
                        "id": ""
                    },
                    "return_format": "array",
                    "library": "all",
                    "min_size": "",
                    "max_size": "",
                    "mime_types": "",
                    "allow_in_bindings": 0
                },
                {
                    "key": "field_67ed05dcf39e4",
                    "label": "TTF",
                    "name": "ttf",
                    "aria-label": "",
                    "type": "file",
                    "instructions": "",
                    "required": 0,
                    "conditional_logic": 0,
                    "wrapper": {
                        "width": "",
                        "class": "",
                        "id": ""
                    },
                    "return_format": "array",
                    "library": "all",
                    "min_size": "",
                    "max_size": "",
                    "mime_types": "",
                    "allow_in_bindings": 0
                }
            ]
        },
        {
            "key": "field_67e6851dfb243",
            "label": "Font Text Bold",
            "name": "fuente_texto_bold",
            "aria-label": "",
            "type": "group",
            "instructions": "",
            "required": 0,
            "conditional_logic": 0,
            "wrapper": {
                "width": "33.33",
                "class": "",
                "id": ""
            },
            "layout": "block",
            "sub_fields": [
                {
                    "key": "field_67e6851dfb244",
                    "label": "WOFF2",
                    "name": "woff2",
                    "aria-label": "",
                    "type": "file",
                    "instructions": "",
                    "required": 0,
                    "conditional_logic": 0,
                    "wrapper": {
                        "width": "",
                        "class": "",
                        "id": ""
                    },
                    "return_format": "",
                    "library": "",
                    "min_size": "",
                    "max_size": "",
                    "mime_types": "",
                    "allow_in_bindings": 0
                },
                {
                    "key": "field_67e6851dfb245",
                    "label": "WOFF",
                    "name": "woff",
                    "aria-label": "",
                    "type": "file",
                    "instructions": "",
                    "required": 0,
                    "conditional_logic": 0,
                    "wrapper": {
                        "width": "",
                        "class": "",
                        "id": ""
                    },
                    "return_format": "",
                    "library": "",
                    "min_size": "",
                    "max_size": "",
                    "mime_types": "",
                    "allow_in_bindings": 0
                },
                {
                    "key": "field_67e6851dfb246",
                    "label": "TTF",
                    "name": "ttf",
                    "aria-label": "",
                    "type": "file",
                    "instructions": "",
                    "required": 0,
                    "conditional_logic": 0,
                    "wrapper": {
                        "width": "",
                        "class": "",
                        "id": ""
                    },
                    "return_format": "",
                    "library": "",
                    "min_size": "",
                    "max_size": "",
                    "mime_types": "",
                    "allow_in_bindings": 0
                }
            ]
        },
        {
            "key": "field_67e68527fb247",
            "label": "Font Text Italic",
            "name": "fuente_texto_italic",
            "aria-label": "",
            "type": "group",
            "instructions": "",
            "required": 0,
            "conditional_logic": 0,
            "wrapper": {
                "width": "33.33",
                "class": "",
                "id": ""
            },
            "layout": "block",
            "sub_fields": [
                {
                    "key": "field_67e68527fb248",
                    "label": "WOFF2",
                    "name": "woff2",
                    "aria-label": "",
                    "type": "file",
                    "instructions": "",
                    "required": 0,
                    "conditional_logic": 0,
                    "wrapper": {
                        "width": "",
                        "class": "",
                        "id": ""
                    },
                    "return_format": "array",
                    "library": "all",
                    "min_size": "",
                    "max_size": "",
                    "mime_types": "",
                    "allow_in_bindings": 0
                },
                {
                    "key": "field_67e68527fb249",
                    "label": "WOFF",
                    "name": "woff",
                    "aria-label": "",
                    "type": "file",
                    "instructions": "",
                    "required": 0,
                    "conditional_logic": 0,
                    "wrapper": {
                        "width": "",
                        "class": "",
                        "id": ""
                    },
                    "return_format": "array",
                    "library": "all",
                    "min_size": "",
                    "max_size": "",
                    "mime_types": "",
                    "allow_in_bindings": 0
                },
                {
                    "key": "field_67e68527fb24a",
                    "label": "TTF",
                    "name": "ttf",
                    "aria-label": "",
                    "type": "file",
                    "instructions": "",
                    "required": 0,
                    "conditional_logic": 0,
                    "wrapper": {
                        "width": "",
                        "class": "",
                        "id": ""
                    },
                    "return_format": "array",
                    "library": "all",
                    "min_size": "",
                    "max_size": "",
                    "mime_types": "",
                    "allow_in_bindings": 0
                }
            ]
        },
        {
            "key": "field_67bf0028d392c",
            "label": "Colours",
            "name": "",
            "aria-label": "",
            "type": "tab",
            "instructions": "",
            "required": 0,
            "conditional_logic": 0,
            "wrapper": {
                "width": "",
                "class": "",
                "id": ""
            },
            "placement": "top",
            "endpoint": 0,
            "selected": 0
        },
        {
            "key": "field_67bf005a47a01",
            "label": "Colour 1",
            "name": "color_1",
            "aria-label": "",
            "type": "color_picker",
            "instructions": "",
            "required": 0,
            "conditional_logic": 0,
            "wrapper": {
                "width": "20",
                "class": "",
                "id": ""
            },
            "default_value": "",
            "enable_opacity": 0,
            "return_format": "string",
            "translations": "copy_once",
            "allow_in_bindings": 0,
            "pll_default_value": ""
        },
        {
            "key": "field_67bf01a947a03",
            "label": "Colour 2",
            "name": "color_2",
            "aria-label": "",
            "type": "color_picker",
            "instructions": "",
            "required": 0,
            "conditional_logic": 0,
            "wrapper": {
                "width": "20",
                "class": "",
                "id": ""
            },
            "default_value": "",
            "enable_opacity": 0,
            "return_format": "string",
            "translations": "copy_once",
            "allow_in_bindings": 0,
            "pll_default_value": ""
        },
        {
            "key": "field_67bf01aa47a04",
            "label": "Colour 3",
            "name": "color_3",
            "aria-label": "",
            "type": "color_picker",
            "instructions": "",
            "required": 0,
            "conditional_logic": 0,
            "wrapper": {
                "width": "20",
                "class": "",
                "id": ""
            },
            "default_value": "",
            "enable_opacity": 0,
            "return_format": "string",
            "translations": "copy_once",
            "allow_in_bindings": 0,
            "pll_default_value": ""
        },
        {
            "key": "field_67bf01af47a05",
            "label": "Colour 4",
            "name": "color_4",
            "aria-label": "",
            "type": "color_picker",
            "instructions": "",
            "required": 0,
            "conditional_logic": 0,
            "wrapper": {
                "width": "20",
                "class": "",
                "id": ""
            },
            "default_value": "",
            "enable_opacity": 0,
            "return_format": "string",
            "translations": "copy_once",
            "allow_in_bindings": 0,
            "pll_default_value": ""
        },
        {
            "key": "field_67bf01b247a06",
            "label": "Colour 5",
            "name": "color_5",
            "aria-label": "",
            "type": "color_picker",
            "instructions": "",
            "required": 0,
            "conditional_logic": 0,
            "wrapper": {
                "width": "20",
                "class": "",
                "id": ""
            },
            "default_value": "",
            "enable_opacity": 0,
            "return_format": "string",
            "translations": "copy_once",
            "allow_in_bindings": 0,
            "pll_default_value": ""
        },
        {
            "key": "field_67bf01b447a07",
            "label": "Colour 6",
            "name": "color_6",
            "aria-label": "",
            "type": "color_picker",
            "instructions": "",
            "required": 0,
            "conditional_logic": 0,
            "wrapper": {
                "width": "20",
                "class": "",
                "id": ""
            },
            "default_value": "",
            "enable_opacity": 0,
            "return_format": "string",
            "translations": "copy_once",
            "allow_in_bindings": 0,
            "pll_default_value": ""
        },
        {
            "key": "field_67bf01b647a08",
            "label": "Colour 7",
            "name": "color_7",
            "aria-label": "",
            "type": "color_picker",
            "instructions": "",
            "required": 0,
            "conditional_logic": 0,
            "wrapper": {
                "width": "20",
                "class": "",
                "id": ""
            },
            "default_value": "",
            "enable_opacity": 0,
            "return_format": "string",
            "translations": "copy_once",
            "allow_in_bindings": 0,
            "pll_default_value": ""
        },
        {
            "key": "field_67bf01b747a09",
            "label": "Colour 8",
            "name": "color_8",
            "aria-label": "",
            "type": "color_picker",
            "instructions": "",
            "required": 0,
            "conditional_logic": 0,
            "wrapper": {
                "width": "20",
                "class": "",
                "id": ""
            },
            "default_value": "",
            "enable_opacity": 0,
            "return_format": "string",
            "translations": "copy_once",
            "allow_in_bindings": 0,
            "pll_default_value": ""
        },
        {
            "key": "field_67cf664deff9e",
            "label": "Colour 9",
            "name": "color_9",
            "aria-label": "",
            "type": "color_picker",
            "instructions": "",
            "required": 0,
            "conditional_logic": 0,
            "wrapper": {
                "width": "20",
                "class": "",
                "id": ""
            },
            "default_value": "",
            "enable_opacity": 0,
            "return_format": "string",
            "translations": "copy_once",
            "allow_in_bindings": 0,
            "pll_default_value": ""
        },
        {
            "key": "field_67cf6652eff9f",
            "label": "Colour 10",
            "name": "color_10",
            "aria-label": "",
            "type": "color_picker",
            "instructions": "",
            "required": 0,
            "conditional_logic": 0,
            "wrapper": {
                "width": "20",
                "class": "",
                "id": ""
            },
            "default_value": "",
            "enable_opacity": 0,
            "return_format": "string",
            "translations": "copy_once",
            "allow_in_bindings": 0,
            "pll_default_value": ""
        },
        {
            "key": "field_68494f3cf1c4b",
            "label": "Images",
            "name": "",
            "aria-label": "",
            "type": "tab",
            "instructions": "",
            "required": 0,
            "conditional_logic": 0,
            "wrapper": {
                "width": "",
                "class": "",
                "id": ""
            },
            "placement": "top",
            "endpoint": 0,
            "selected": 0
        },
        {
            "key": "field_68494f57f1c4c",
            "label": "Header logo",
            "name": "header_logo",
            "aria-label": "",
            "type": "image",
            "instructions": "",
            "required": 0,
            "conditional_logic": 0,
            "wrapper": {
                "width": "",
                "class": "",
                "id": ""
            },
            "return_format": "url",
            "library": "all",
            "translations": "copy_once",
            "min_width": "",
            "min_height": "",
            "min_size": "",
            "max_width": "",
            "max_height": "",
            "max_size": "",
            "mime_types": "",
            "allow_in_bindings": 0,
            "preview_size": "medium"
        },
        {
            "key": "field_68494f8dc93df",
            "label": "Archives background",
            "name": "archives_background",
            "aria-label": "",
            "type": "image",
            "instructions": "",
            "required": 0,
            "conditional_logic": 0,
            "wrapper": {
                "width": "",
                "class": "",
                "id": ""
            },
            "return_format": "url",
            "library": "all",
            "translations": "copy_once",
            "min_width": "",
            "min_height": "",
            "min_size": "",
            "max_width": "",
            "max_height": "",
            "max_size": "",
            "mime_types": "",
            "allow_in_bindings": 0,
            "preview_size": "medium"
        },
        {
            "key": "field_67bf07c788375",
            "label": "Other design adjustments",
            "name": "",
            "aria-label": "",
            "type": "tab",
            "instructions": "",
            "required": 0,
            "conditional_logic": 0,
            "wrapper": {
                "width": "",
                "class": "",
                "id": ""
            },
            "placement": "top",
            "endpoint": 0,
            "selected": 0
        },
        {
            "key": "field_67bf07de88376",
            "label": "Containers radio border",
            "name": "contenedores_borde_radio",
            "aria-label": "",
            "type": "number",
            "instructions": "",
            "required": 0,
            "conditional_logic": 0,
            "wrapper": {
                "width": "50",
                "class": "",
                "id": ""
            },
            "default_value": 0,
            "translations": "copy_once",
            "min": "",
            "max": "",
            "allow_in_bindings": 0,
            "placeholder": "",
            "step": "",
            "prepend": "",
            "append": "",
            "pll_default_value": 0
        },
        {
            "key": "field_67bf081ac84c7",
            "label": "Buttons radio border",
            "name": "botones_borde_radio",
            "aria-label": "",
            "type": "number",
            "instructions": "",
            "required": 0,
            "conditional_logic": 0,
            "wrapper": {
                "width": "50",
                "class": "",
                "id": ""
            },
            "default_value": 0,
            "translations": "copy_once",
            "min": "",
            "max": "",
            "allow_in_bindings": 0,
            "placeholder": "",
            "step": "",
            "prepend": "",
            "append": "",
            "pll_default_value": 0
        },
        {
            "key": "field_68528bb1133a6",
            "label": "Scripts",
            "name": "",
            "aria-label": "",
            "type": "tab",
            "instructions": "",
            "required": 0,
            "conditional_logic": 0,
            "wrapper": {
                "width": "",
                "class": "",
                "id": ""
            },
            "placement": "top",
            "endpoint": 0,
            "selected": 0
        },
        {
            "key": "field_68528bb9133a7",
            "label": "Scripts Header",
            "name": "scripts_header",
            "aria-label": "",
            "type": "textarea",
            "instructions": "",
            "required": 0,
            "conditional_logic": 0,
            "wrapper": {
                "width": "",
                "class": "",
                "id": ""
            },
            "default_value": "",
            "translations": "translate",
            "maxlength": "",
            "allow_in_bindings": 0,
            "rows": "",
            "placeholder": "",
            "new_lines": "",
            "pll_default_value": ""
        },
        {
            "key": "field_68528bc4133a8",
            "label": "Scripts Body",
            "name": "scripts_body",
            "aria-label": "",
            "type": "textarea",
            "instructions": "",
            "required": 0,
            "conditional_logic": 0,
            "wrapper": {
                "width": "",
                "class": "",
                "id": ""
            },
            "default_value": "",
            "translations": "translate",
            "maxlength": "",
            "allow_in_bindings": 0,
            "rows": "",
            "placeholder": "",
            "new_lines": "",
            "pll_default_value": ""
        }
    ],
    "location": [
        [
            {
                "param": "options_page",
                "operator": "==",
                "value": "configuracion"
            }
        ]
    ],
    "menu_order": 0,
    "position": "normal",
    "style": "default",
    "label_placement": "top",
    "instruction_placement": "label",
    "hide_on_screen": "",
    "active": true,
    "description": "",
    "show_in_rest": 0,
    "pll_display_field_instructions": 1,
    "modified": 1750240231
}
